psfed/__init__.py
psfed/py.typed
psfed/core/__init__.py
psfed/core/flattener.py
psfed/core/mask.py
psfed/core/selectors.py
psfed/flower/__init__.py
psfed/flower/client.py
psfed/flower/numpy_utils.py
psfed/flower/strategy.py
psfed/utils/__init__.py
psfed/utils/validation.py
psfed-0.1.2.dist-info/METADATA
psfed-0.1.2.dist-info/WHEEL
psfed-0.1.2.dist-info/licenses/LICENSE
psfed-0.1.2.dist-info/RECORD
