Metadata-Version: 2.4
Name: psfed
Version: 0.1.2
Summary: Partial Model Sharing for Federated Learning - A PyTorch and Flower extension
Project-URL: Homepage, https://github.com/ehsan-lari/psfed
Project-URL: Documentation, https://github.com/ehsan-lari/psfed#readme
Project-URL: Repository, https://github.com/ehsan-lari/psfed
Project-URL: Issues, https://github.com/ehsan-lari/psfed/issues
Author-email: Ehsan <your.email@example.com>
License-Expression: MIT
License-File: LICENSE
Keywords: communication-efficient,federated-learning,flower,machine-learning,partial-sharing,pytorch
Classifier: Development Status :: 3 - Alpha
Classifier: Intended Audience :: Developers
Classifier: Intended Audience :: Science/Research
Classifier: License :: OSI Approved :: MIT License
Classifier: Operating System :: OS Independent
Classifier: Programming Language :: Python :: 3
Classifier: Programming Language :: Python :: 3.10
Classifier: Programming Language :: Python :: 3.11
Classifier: Programming Language :: Python :: 3.12
Classifier: Topic :: Scientific/Engineering :: Artificial Intelligence
Classifier: Typing :: Typed
Requires-Python: >=3.10
Requires-Dist: flwr>=1.5.0
Requires-Dist: numpy>=1.24.0
Requires-Dist: torch>=2.0.0
Provides-Extra: dev
Requires-Dist: mypy>=1.0.0; extra == 'dev'
Requires-Dist: pre-commit>=3.0.0; extra == 'dev'
Requires-Dist: pytest-cov>=4.0.0; extra == 'dev'
Requires-Dist: pytest>=7.0.0; extra == 'dev'
Requires-Dist: ruff>=0.1.0; extra == 'dev'
Provides-Extra: docs
Requires-Dist: mkdocs-material>=9.0.0; extra == 'docs'
Requires-Dist: mkdocs>=1.5.0; extra == 'docs'
Requires-Dist: mkdocstrings[python]>=0.24.0; extra == 'docs'
